{
    "bootstrap_servers": ["localhost:9092"],
    "auto_offset_reset": "latest",
    "enable_auto_commit": "True",
    "group_id": "my-group",
    "value_deserializer": "lambda x: loads(x.decode('utf-8'))",
    "topics": ["anomaly_detection"],
    "anomaly_detection_alg": "EMA()",
    "anomaly_detection_conf": {
        "N": 5,
        "num_of_points": 50,
        "output": ["TerminalOutput()"],
        "output_conf": [
            {}
        ],
        "visualization": ["GraphVisualization()"],
        "visualization_conf":[
            {
                "num_of_points": 50,
                "num_of_lines": 4,
                "linestyles":["wo", "r-", "b--", "b--"]
            },
            {
                "num_of_bins": 50,
                "range": [0, 10]
            }
        ]
    }
}